is_x/__init__.py
is_x/core/__init__.py
is_x/core/approximate.py
is_x/core/basic.py
is_x/core/math_basic.py
is_x_py-0.0.1.dist-info/METADATA
is_x_py-0.0.1.dist-info/WHEEL
is_x_py-0.0.1.dist-info/top_level.txt
is_x_py-0.0.1.dist-info/RECORD
