Metadata-Version: 2.1
Name: is-x-py
Version: 0.0.1
Summary: Python implementation of is-x library
Home-page: https://github.com/deidaraiorek/is-x/packages/is-x-py
Author: Dang Pham
Author-email: danghuuphamusf@gmail.com
Classifier: Programming Language :: Python :: 3
